nodie/__init__.py
nodie/constants/css_properties.py
nodie/constants/html_tag_mappers.py
nodie/constants/types.py
nodie/converters/__init__.py
nodie/converters/html_converter.py
nodie/helpers/__init__.py
nodie/helpers/helpers.py
nodie/primitives/__init__.py
nodie/primitives/attributes.py
nodie/primitives/inline_style_attributes.py
nodie/primitives/node.py
nodie/protocols/__init__.py
nodie/protocols/attrs_protocols.py
nodie/tests/tests_node.py
nodie-0.0.2.dist-info/METADATA
nodie-0.0.2.dist-info/WHEEL
nodie-0.0.2.dist-info/licenses/LICENSE
nodie-0.0.2.dist-info/RECORD
